<?xml version="1.0" encoding="utf-8"?>
<doctrine-mapping xmlns="http://doctrine-project.org/schemas/orm/doctrine-mapping" xmlns:xsi="http://www.w3.org/2001/XMLSchema-instance" xsi:schemaLocation="http://doctrine-project.org/schemas/orm/doctrine-mapping https://www.doctrine-project.org/schemas/orm/doctrine-mapping.xsd">
  <entity name="SvyQstMetric" table="svy_qst_metric">
    <id name="questionFi" type="integer" column="question_fi">
      <generator strategy="IDENTITY"/>
    </id>
    <field name="subtype" type="string" column="subtype" length="1" nullable="true">
      <options>
        <option name="fixed"/>
        <option name="default">3</option>
      </options>
    </field>
  </entity>
</doctrine-mapping>
